unikraft_cloud_platform/__init__.py
unikraft_cloud_platform/api/__init__.py
unikraft_cloud_platform/api/autoscale/__init__.py
unikraft_cloud_platform/api/autoscale/create_autoscale_configuration_by_service_group_uuid.py
unikraft_cloud_platform/api/autoscale/create_autoscale_configuration_policy.py
unikraft_cloud_platform/api/autoscale/create_autoscale_configurations.py
unikraft_cloud_platform/api/autoscale/delete_autoscale_configuration_policies.py
unikraft_cloud_platform/api/autoscale/delete_autoscale_configuration_policy_by_name.py
unikraft_cloud_platform/api/autoscale/delete_autoscale_configurations.py
unikraft_cloud_platform/api/autoscale/delete_autoscale_configurations_by_service_group_uuid.py
unikraft_cloud_platform/api/autoscale/get_autoscale_configuration_policies.py
unikraft_cloud_platform/api/autoscale/get_autoscale_configuration_policy_by_name.py
unikraft_cloud_platform/api/autoscale/get_autoscale_configurations.py
unikraft_cloud_platform/api/autoscale/get_autoscale_configurations_by_service_group_uuid.py
unikraft_cloud_platform/api/certificates/__init__.py
unikraft_cloud_platform/api/certificates/create_certificate.py
unikraft_cloud_platform/api/certificates/delete_certificate_by_uuid.py
unikraft_cloud_platform/api/certificates/delete_certificates.py
unikraft_cloud_platform/api/certificates/get_certificate_by_uuid.py
unikraft_cloud_platform/api/certificates/get_certificates.py
unikraft_cloud_platform/api/images/__init__.py
unikraft_cloud_platform/api/images/get_image_by_digest.py
unikraft_cloud_platform/api/images/get_image_by_tag.py
unikraft_cloud_platform/api/instances/__init__.py
unikraft_cloud_platform/api/instances/create_instance.py
unikraft_cloud_platform/api/instances/delete_instance_by_uuid.py
unikraft_cloud_platform/api/instances/delete_instances.py
unikraft_cloud_platform/api/instances/get_instance_by_uuid.py
unikraft_cloud_platform/api/instances/get_instance_logs.py
unikraft_cloud_platform/api/instances/get_instance_logs_by_uuid.py
unikraft_cloud_platform-1.0.0.dist-info/WHEEL
unikraft_cloud_platform-1.0.0.dist-info/METADATA
unikraft_cloud_platform-1.0.0.dist-info/RECORD
