Metadata-Version: 2.3
Name: unikraft-cloud-platform
Version: 1.0.0
Summary: A client library for accessing Unikraft Cloud Platform API
Requires-Dist: httpx>=0.23.0,<0.29.0
Requires-Dist: attrs>=22.2.0
Requires-Dist: python-dateutil>=2.8.0,<3
Requires-Python: >=3.9, <4.0
